{
	"Customers": [
		{
			"4#java.lang.String#_firstName": "Joe",
			"6#java.lang.String#_gender": "M",
			"2#java.lang.String#_username": "hahaha",
			"5#java.lang.String#_lastName": "John",
			"7#java.lang.String#_phoneNumber": "jdldffsd",
			"type": "backend.auth.Customer",
			"3#java.lang.String#_password": "ENCRIPTED:!46575!76286!71975!76572!16282!61978",
			"1#java.lang.Integer#_userId": 7
		},
		{
			"4#java.lang.String#_firstName": "Ian",
			"6#java.lang.String#_gender": "M",
			"2#java.lang.String#_username": "ianmann56",
			"5#java.lang.String#_lastName": "Kirkpatrick",
			"7#java.lang.String#_phoneNumber": "jdldffsd",
			"type": "backend.auth.Customer",
			"3#java.lang.String#_password": "ENCRIPTED:*63149*90241!56571!19189!84875!15082!38273!34582",
			"1#java.lang.Integer#_userId": 8
		},
		{
			"4#java.lang.String#_firstName": "Ian",
			"6#java.lang.String#_gender": "Male",
			"2#java.lang.String#_username": "ianmann99",
			"5#java.lang.String#_lastName": "Kirkpatrick",
			"7#java.lang.String#_phoneNumber": "flsjflsa",
			"type": "backend.auth.Customer",
			"3#java.lang.String#_password": "ENCRIPTED:*13141*30249!86579!59184!14874!55082!28273!14581",
			"1#java.lang.Integer#_userId": 9
		}
	],
	"nextUserId": "10"
}
